g2p_plus/__init__.py
g2p_plus/main.py
g2p_plus/data/cedict_ts.u8
g2p_plus/data/pingyam/LICENSE
g2p_plus/data/pingyam/README.md
g2p_plus/data/pingyam/pingyambiu
g2p_plus/folding/epitran/cmn-Hans.csv
g2p_plus/folding/epitran/cmn-Latn.csv
g2p_plus/folding/epitran/deu-Latn.csv
g2p_plus/folding/epitran/epitran.csv
g2p_plus/folding/epitran/hrv-Latn.csv
g2p_plus/folding/epitran/hun-Latn.csv
g2p_plus/folding/epitran/ind-Latn.csv
g2p_plus/folding/epitran/spa-Latn.csv
g2p_plus/folding/epitran/srp-Latn.csv
g2p_plus/folding/epitran/yue-Latn.csv
g2p_plus/folding/phonemizer/ca.csv
g2p_plus/folding/phonemizer/cy.csv
g2p_plus/folding/phonemizer/da.csv
g2p_plus/folding/phonemizer/de.csv
g2p_plus/folding/phonemizer/en-gb.csv
g2p_plus/folding/phonemizer/en-us.csv
g2p_plus/folding/phonemizer/et.csv
g2p_plus/folding/phonemizer/eu.csv
g2p_plus/folding/phonemizer/fa-latn.csv
g2p_plus/folding/phonemizer/fr-fr.csv
g2p_plus/folding/phonemizer/ga.csv
g2p_plus/folding/phonemizer/id.csv
g2p_plus/folding/phonemizer/is.csv
g2p_plus/folding/phonemizer/it.csv
g2p_plus/folding/phonemizer/ja.csv
g2p_plus/folding/phonemizer/ko.csv
g2p_plus/folding/phonemizer/nb.csv
g2p_plus/folding/phonemizer/nl.csv
g2p_plus/folding/phonemizer/phonemizer.csv
g2p_plus/folding/phonemizer/pl.csv
g2p_plus/folding/phonemizer/pt-br.csv
g2p_plus/folding/phonemizer/pt.csv
g2p_plus/folding/phonemizer/qu.csv
g2p_plus/folding/phonemizer/ro.csv
g2p_plus/folding/phonemizer/sv.csv
g2p_plus/folding/phonemizer/tr.csv
g2p_plus/folding/pingyam/pingyam.csv
g2p_plus/folding/pinyin_to_ipa/pinyin_to_ipa.csv
g2p_plus/wrappers/__init__.py
g2p_plus/wrappers/epitran_wrapper.py
g2p_plus/wrappers/phonemizer_wrapper.py
g2p_plus/wrappers/pingyam_wrapper.py
g2p_plus/wrappers/pinyin_to_ipa_wrapper.py
g2p_plus/wrappers/wrapper.py
g2p_plus-0.1.6.dist-info/licenses/LICENSE
g2p_plus-0.1.6.dist-info/METADATA
g2p_plus-0.1.6.dist-info/WHEEL
g2p_plus-0.1.6.dist-info/entry_points.txt
g2p_plus-0.1.6.dist-info/top_level.txt
g2p_plus-0.1.6.dist-info/RECORD
