Metadata-Version: 2.4
Name: g2p_plus
Version: 0.1.6
Summary: G2P library for multiple language
Author-email: Zebulon Goriely <zebulon.goriely@cl.cam.ac.uk>
License: MIT License
Project-URL: Homepage, https://github.com/codebyzeb/g2p-plus
Project-URL: Issues, https://github.com/codebyzeb/g2p-plus/issues
Keywords: G2P,phonology,phonetics,linguistics,phone
Classifier: Development Status :: 1 - Planning
Classifier: Intended Audience :: Science/Research
Classifier: Operating System :: OS Independent
Classifier: Programming Language :: Python :: 3
Requires-Python: >=3.8
License-File: LICENSE
Requires-Dist: epitran>=1.25.1
Requires-Dist: phonemizer>=3.2.1
Requires-Dist: pinyin-to-ipa>=0.0.2
Dynamic: license-file
